ffpp/Discovery.py
ffpp/Network.py
ffpp/Printer.py
ffpp/__init__.py
ffpp-0.0.15.dist-info/licenses/LICENSE
ffpp-0.0.15.dist-info/METADATA
ffpp-0.0.15.dist-info/WHEEL
ffpp-0.0.15.dist-info/top_level.txt
ffpp-0.0.15.dist-info/RECORD
