Metadata-Version: 2.4
Name: ffpp
Version: 0.0.15
Summary: A simple way to connect and interact with your 3D printer.
Home-page: https://github.com/joseffallman/ffpp
Author: Josef Fällman
Author-email: josef.fallman@gmail.com
Project-URL: Bug Tracker, https://github.com/joseffallman/ffpp/issues
Classifier: Programming Language :: Python :: 3
Classifier: License :: OSI Approved :: MIT License
Classifier: Operating System :: OS Independent
Requires-Python: >=3.8
License-File: LICENSE
Dynamic: license-file
